tango_shared/__init__.py
tango_shared/context_processors.py
tango_shared/debug_settings.py
tango_shared/middleware.py
tango_shared/models.py
tango_shared/settings.py
tango_shared/tests.py
tango_shared/views.py
tango_shared/static/js/shared-core.js
tango_shared/static/libs/jquery.markitup.js
tango_shared/static/libs/modernizr-3.1.0.min.js
tango_shared/static/libs/tango-markitup-min.js
tango_shared/static/source/tango_markitup.js
tango_shared/templates/base.html
tango_shared/templates/base_all.html
tango_shared/templates/index.html
tango_shared/templates/includes/formatted_time.html
tango_shared/templates/includes/fresh_content.html
tango_shared/templates/includes/generic_pagination.html
tango_shared/templates/includes/signin.html
tango_shared/templates/includes/site_nav.html
tango_shared/templates/includes/social_links.html
tango_shared/templates/includes/top_assets.html
tango_shared/templatetags/__init__.py
tango_shared/templatetags/formatting.py
tango_shared/templatetags/social_tags.py
tango_shared/templatetags/tango_site_tags.py
tango_shared/templatetags/tango_time_tags.py
tango_shared/utils/__init__.py
tango_shared/utils/maptools.py
tango_shared/utils/sanetize.py
tango_shared_core-1.5.0.dist-info/METADATA
tango_shared_core-1.5.0.dist-info/RECORD
tango_shared_core-1.5.0.dist-info/WHEEL
tango_shared_core-1.5.0.dist-info/top_level.txt
