Metadata-Version: 1.1
Name: tango-shared-core
Version: 1.5.0
Summary: Tango shared/core functionality.
Home-page: https://github.com/tBaxter/tango-shared-core
Author: Tim Baxter
Author-email: mail.baxter@gmail.com
License: MIT
Platform: UNKNOWN
Classifier: Development Status :: 4 - Beta
Classifier: Environment :: Web Environment
Classifier: Framework :: Django
Classifier: Intended Audience :: Developers
Classifier: License :: OSI Approved :: MIT License
Classifier: Programming Language :: Python
Classifier: Programming Language :: Python :: 2.7
Classifier: Programming Language :: Python :: 3.4
